{
  "$schema": "https://wails.io/schemas/config.v2.json",
  "name": "robo-stream-server",
  "outputfilename": "robo-stream-server",
  "frontend:install": "npm install",
  "frontend:build": "npm run build",
  "frontend:dev:watcher": "npm run dev",
  "frontend:dev:serverUrl": "auto",
  "author": {
    "name": "Robomon",
    "email": ""
  },
  "info": {
    "companyName": "Robomon",
    "productName": "Robo-Stream Server",
    "productVersion": "1.0.0",
    "copyright": "Copyright © 2024",
    "comments": "OBS Stream Deck Server"
  }
}
